Metadata-Version: 1.1
Name: bob.ip.mtcnn
Version: 1.0.3
Summary: Face detection and landmark extraction using MTCNN pretrained model
Home-page: https://gitlab.idiap.ch/bob/bob.ip.mtcnn
Author: Tiago de Freitas Pereira
Author-email: tiago.pereira@idiap.ch
License: BSD
Keywords: bob,biometric recognition,evaluation
Platform: UNKNOWN
Classifier: Framework :: Bob
Classifier: Development Status :: 3 - Alpha
Classifier: Intended Audience :: Developers
Classifier: License :: OSI Approved :: BSD License
Classifier: Natural Language :: English
Classifier: Programming Language :: Python
Classifier: Topic :: Scientific/Engineering :: Artificial Intelligence
